hack4u/__init__.py
hack4u/courses.py
hack4u/utils.py
hack4upolsiv-0.1.2.dist-info/METADATA
hack4upolsiv-0.1.2.dist-info/WHEEL
hack4upolsiv-0.1.2.dist-info/top_level.txt
hack4upolsiv-0.1.2.dist-info/RECORD
