Metadata-Version: 2.1
Name: hack4upolsiv
Version: 0.1.2
Summary: Library for hack4u courses
Home-page: https://hack4u.io
Author: Polsiv
